CMakeLists.txt
README.md
pyproject.toml
setup.py
src/CMakeLists.txt
src/core/CMakeLists.txt
src/core/all_cases/all_cases.h
src/core/all_cases/all_cases_fwd.h
src/core/all_cases/internal/all_cases.cc
src/core/all_cases/internal/all_cases.inl
src/core/all_cases/internal/basic_ranges.cc
src/core/all_cases/internal/basic_ranges.inl
src/core/all_cases/internal/constant.inl
src/core/analyse/analyse.cc
src/core/analyse/analyse.h
src/core/analyse/backtrack.cc
src/core/common_code/common_code.h
src/core/common_code/common_code_fwd.h
src/core/common_code/internal/check.inl
src/core/common_code/internal/common_code.inl
src/core/common_code/internal/mirror.inl
src/core/common_code/internal/serialize.inl
src/core/fast_cal/fast_cal.h
src/core/fast_cal/layer_queue.h
src/core/fast_cal/internal/fast_cal.cc
src/core/fast_cal/internal/fast_cal.inl
src/core/fast_cal/internal/layer_queue.inl
src/core/group/group.h
src/core/group/group_fwd.h
src/core/group/internal/case_info.inl
src/core/group/internal/group.cc
src/core/group/internal/group.inl
src/core/group/internal/group_cases.cc
src/core/group/internal/group_cases.inl
src/core/group/internal/group_union.cc
src/core/group/internal/group_union.inl
src/core/group/internal/mirror.inl
src/core/group/internal/type_id.inl
src/core/group/internal/constant/group.h
src/core/group/internal/constant/group.inc
src/core/group/internal/constant/group_union.h
src/core/group/internal/constant/pattern.inc
src/core/mover/mover.h
src/core/mover/internal/mover.cc
src/core/ranges/ranges.h
src/core/ranges/ranges_fwd.h
src/core/ranges/internal/check.inl
src/core/ranges/internal/ranges.cc
src/core/ranges/internal/ranges.inl
src/core/ranges/internal/spawn.cc
src/core/raw_code/raw_code.h
src/core/raw_code/raw_code_fwd.h
src/core/raw_code/internal/check.inl
src/core/raw_code/internal/convert.inl
src/core/raw_code/internal/mirror.inl
src/core/raw_code/internal/raw_code.inl
src/core/short_code/short_code.h
src/core/short_code/short_code_fwd.h
src/py_klotski.egg-info/PKG-INFO
src/py_klotski.egg-info/SOURCES.txt
src/py_klotski.egg-info/dependency_links.txt
src/py_klotski.egg-info/top_level.txt
