Metadata-Version: 2.1
Name: py-klotski
Version: 0.0.2
Summary: Klotski multifunctional engine with high performance
Author-email: Dnomd343 <dnomd343@gmail.com>
Maintainer-email: Dnomd343 <dnomd343@gmail.com>
License: BSD-3-Clause
Project-URL: Source, https://github.com/dnomd343/klotski.git
Project-URL: Tracker, https://github.com/dnomd343/klotski/issues
Project-URL: Changelog, https://github.com/dnomd343/klotski/blob/master/CHANGELOG.md
Classifier: Development Status :: 2 - Pre-Alpha
Classifier: License :: OSI Approved :: BSD License
Classifier: Topic :: Games/Entertainment
Classifier: Topic :: Software Development
Classifier: Topic :: Scientific/Engineering
Classifier: Intended Audience :: Education
Classifier: Intended Audience :: Developers
Classifier: Intended Audience :: Science/Research
Classifier: Operating System :: MacOS
Classifier: Operating System :: POSIX
Classifier: Programming Language :: C++
Classifier: Programming Language :: Python :: 3
Classifier: Programming Language :: Python :: 3.7
Classifier: Programming Language :: Python :: 3.8
Classifier: Programming Language :: Python :: 3.9
Classifier: Programming Language :: Python :: 3.10
Classifier: Programming Language :: Python :: 3.11
Classifier: Programming Language :: Python :: 3.12
Classifier: Programming Language :: Python :: 3.13
Classifier: Programming Language :: Python :: 3 :: Only
Requires-Python: >=3.7
